toxic/__init__.py
toxic/toxic.py
checktoxicity-0.1.2.dist-info/LICENSE
checktoxicity-0.1.2.dist-info/METADATA
checktoxicity-0.1.2.dist-info/WHEEL
checktoxicity-0.1.2.dist-info/top_level.txt
checktoxicity-0.1.2.dist-info/RECORD
